pytml5/Webgets.py
pytml5/__init__.py
pytml5/__main__.py
PyTML5-1.0.0b1.dist-info/METADATA
PyTML5-1.0.0b1.dist-info/WHEEL
PyTML5-1.0.0b1.dist-info/top_level.txt
PyTML5-1.0.0b1.dist-info/RECORD
