Metadata-Version: 2.1
Name: PyTML5
Version: 1.0.0b1
Summary: This is PyTML5, a module for writing HTML using Python.
Home-page: https://boodywin.github.io/PyTML5
Author: BoodyWin Workshop
Author-email: boodywin.studio.123@gmail.com
License: 
Project-URL: Bug Tracker, https://github.com/BoodyWin/PyTML5/issues
Project-URL: Documentation, https://boodywin.github.io/PyTML5/Docs
Keywords: HTML,Python to HTML,HTML generation
Classifier: Development Status :: 4 - Beta
Classifier: Intended Audience :: Developers
Classifier: License :: OSI Approved :: MIT License
Classifier: Programming Language :: Python :: 3
Classifier: Programming Language :: Python :: 3.6
Classifier: Programming Language :: Python :: 3.7
Classifier: Programming Language :: Python :: 3.8
Classifier: Programming Language :: Python :: 3.9
Classifier: Programming Language :: Python :: 3.10
Classifier: Programming Language :: Python :: 3.11
